gentun/__init__.py
gentun/algorithms.py
gentun/config.py
gentun/genes.py
gentun/individuals.py
gentun/populations.py
gentun/services.py
gentun/models/__init__.py
gentun/models/base.py
gentun/models/sklearn.py
gentun/models/tensorflow.py
gentun/models/xgboost.py
gentun-0.0.3.dist-info/LICENSE
gentun-0.0.3.dist-info/WHEEL
gentun-0.0.3.dist-info/METADATA
gentun-0.0.3.dist-info/RECORD
