Metadata-Version: 2.1
Name: gentun
Version: 0.0.3
Summary: Hyperparameter tuning for machine learning models using a distributed genetic algorithm
Author: Gustavo Montamat
Requires-Python: >=3.8.1
Classifier: Development Status :: 3 - Alpha
Classifier: Intended Audience :: Science/Research
Classifier: Topic :: Scientific/Engineering :: Artificial Intelligence
Classifier: License :: OSI Approved :: Apache Software License
Classifier: Programming Language :: Python :: 3 :: Only
Classifier: Programming Language :: Python :: 3.8
Classifier: Programming Language :: Python :: 3.9
Classifier: Programming Language :: Python :: 3.10
Classifier: Programming Language :: Python :: 3.11
Requires-Dist: redis
Requires-Dist: scikit-learn
Requires-Dist: numpy<2
Requires-Dist: tensorflow>=2.0.0 ; extra == "tensorflow"
Requires-Dist: pydot ; extra == "tensorflow"
Requires-Dist: bandit[toml]==1.7.5 ; extra == "test"
Requires-Dist: black==23.3.0 ; extra == "test"
Requires-Dist: check-manifest==0.49 ; extra == "test"
Requires-Dist: flake8-bugbear==23.5.9 ; extra == "test"
Requires-Dist: flake8-docstrings ; extra == "test"
Requires-Dist: flake8-formatter_junit_xml ; extra == "test"
Requires-Dist: flake8 ; extra == "test"
Requires-Dist: flake8-pyproject ; extra == "test"
Requires-Dist: pre-commit==3.3.1 ; extra == "test"
Requires-Dist: pylint==2.17.4 ; extra == "test"
Requires-Dist: pylint_junit ; extra == "test"
Requires-Dist: pytest-cov==4.0.0 ; extra == "test"
Requires-Dist: pytest-mock<3.10.1 ; extra == "test"
Requires-Dist: pytest-runner ; extra == "test"
Requires-Dist: pytest==7.3.1 ; extra == "test"
Requires-Dist: pytest-github-actions-annotate-failures ; extra == "test"
Requires-Dist: shellcheck-py==0.9.0.2 ; extra == "test"
Requires-Dist: xgboost ; extra == "xgboost"
Project-URL: Documentation, https://github.com/gmontamat/gentun/tree/main#readme
Project-URL: Source, https://github.com/gmontamat/gentun
Project-URL: Tracker, https://github.com/gmontamat/gentun/issues
Provides-Extra: tensorflow
Provides-Extra: test
Provides-Extra: xgboost
